Browse_win_package/__init__.py
Browse_win_package/main.py
Browse_win-0.0.1.dist-info/LICENSE
Browse_win-0.0.1.dist-info/METADATA
Browse_win-0.0.1.dist-info/WHEEL
Browse_win-0.0.1.dist-info/entry_points.txt
Browse_win-0.0.1.dist-info/top_level.txt
Browse_win-0.0.1.dist-info/RECORD
