Metadata-Version: 2.1
Name: Browse_win
Version: 0.0.1
Summary: A Python script for uploading files using browse_win module
Home-page: https://github.com/Priyansh-03/Browse-Window--python
Author: Priyansh Srivastava
Classifier: Programming Language :: Python :: 3
Classifier: License :: OSI Approved :: MIT License
Classifier: Operating System :: OS Independent
Requires-Python: >=3.7
License-File: LICENSE
